dumbo_utils/__init__.py
dumbo_utils/console.py
dumbo_utils/files.py
dumbo_utils/logging.py
dumbo_utils/objects.py
dumbo_utils/primitives.py
dumbo_utils/url.py
dumbo_utils/validation.py
dumbo_utils-0.3.6.dist-info/LICENSE
dumbo_utils-0.3.6.dist-info/METADATA
dumbo_utils-0.3.6.dist-info/WHEEL
dumbo_utils-0.3.6.dist-info/RECORD
