Metadata-Version: 2.1
Name: dumbo-utils
Version: 0.3.6
Summary: Different utilities to be reused in other projects
Author: Mario Alviano
Author-email: mario.alviano@gmail.com
Requires-Python: >=3.11,<4.0
Classifier: Programming Language :: Python :: 3
Classifier: Programming Language :: Python :: 3.11
Classifier: Programming Language :: Python :: 3.12
Requires-Dist: dataclass-type-validator (>=0.1.2,<0.2.0)
Requires-Dist: distlib (>=0.3.8,<0.4.0)
Requires-Dist: rich (>=13.7.1,<14.0.0)
Requires-Dist: typeguard (>=4.2.1,<5.0.0)
Requires-Dist: typer (>=0.12.3,<0.13.0)
Requires-Dist: valid8 (>=5.1.2,<6.0.0)
